{
  "_version": "2.0",
  "_description": "Smart Suite 智库 Agent - 画像矩阵配置。用于组合推演检索短语。",
  "_updated": "2026-07-10",

  "基础画像": {
    "身份": {
      "params": ["新卖家(P2L以前)", "新卖家(P2L)", "新卖家(L2L)", "1年以下卖家", "1-2年卖家", "2-3年卖家", "3年以上卖家", "服务商"],
      "priority_weight": {
        "新卖家(P2L以前)": 5, "新卖家(P2L)": 5, "新卖家(L2L)": 4,
        "1年以下卖家": 4, "1-2年卖家": 3, "2-3年卖家": 2, "3年以上卖家": 2, "服务商": 1
      },
      "search_volume_multiplier": {
        "新卖家(P2L以前)": 3.0, "新卖家(P2L)": 2.5, "新卖家(L2L)": 2.0,
        "1年以下卖家": 1.8, "1-2年卖家": 1.5, "2-3年卖家": 1.2, "3年以上卖家": 1.0, "服务商": 0.5
      }
    },
    "企业类型": {
      "params": ["有品牌有工厂", "有品牌有合作工厂", "自有工厂无品牌", "经销商/分销商", "个人", "其他"],
      "priority_weight": {
        "有品牌有工厂": 5, "有品牌有合作工厂": 4, "自有工厂无品牌": 4,
        "经销商/分销商": 3, "个人": 3, "其他": 1
      }
    },
    "职位": {
      "params": ["管理者", "运营者", "其他"],
      "priority_weight": {"管理者": 4, "运营者": 5, "其他": 2}
    },
    "年销售额": {
      "params": ["500W以下", "1000W以下", "1000W以上", "1亿以上"],
      "priority_weight": {"500W以下": 5, "1000W以下": 4, "1000W以上": 3, "1亿以上": 2}
    },
    "公司类型": {
      "params": ["工厂", "贸易商", "品牌方", "服务商或其他"],
      "priority_weight": {"工厂": 4, "贸易商": 4, "品牌方": 5, "服务商或其他": 2}
    },
    "计划发货方式": {
      "params": ["FBA", "自发货", "还没决定"],
      "priority_weight": {"FBA": 5, "自发货": 3, "还没决定": 4}
    }
  },

  "兴趣画像": {
    "站点": {
      "params": ["美国站", "加拿大站", "墨西哥站", "英国站", "德国站", "法国站", "意大利站", "西班牙站", "日本站", "阿联酋站", "沙特站", "巴西站", "澳洲站", "印度站", "土耳其站", "荷兰站", "瑞典站", "波兰站", "比利时站"],
      "priority_weight": {
        "美国站": 5, "加拿大站": 4, "墨西哥站": 3,
        "英国站": 4, "德国站": 4, "法国站": 3, "意大利站": 3, "西班牙站": 3,
        "日本站": 4,
        "阿联酋站": 3, "沙特站": 3,
        "巴西站": 2, "澳洲站": 3, "印度站": 2,
        "土耳其站": 2, "荷兰站": 2, "瑞典站": 2, "波兰站": 2, "比利时站": 2
      },
      "search_volume_multiplier": {
        "美国站": 3.0, "加拿大站": 1.5, "墨西哥站": 1.2,
        "英国站": 2.0, "德国站": 2.0, "法国站": 1.5, "意大利站": 1.3, "西班牙站": 1.3,
        "日本站": 2.0,
        "阿联酋站": 1.5, "沙特站": 1.5,
        "巴西站": 1.0, "澳洲站": 1.5, "印度站": 1.0,
        "土耳其站": 0.8, "荷兰站": 0.8, "瑞典站": 0.8, "波兰站": 0.8, "比利时站": 0.8
      }
    },
    "内容分类": {
      "params": ["新手指南", "选品", "合规", "物流仓储", "品牌打造", "旺季与流量", "企业购", "卖家百科", "卖家成长服务", "工厂专区", "跨境收付款", "品类洞察", "广告推广"],
      "priority_weight": {
        "新手指南": 5, "选品": 4, "合规": 4, "物流仓储": 4, "品牌打造": 3,
        "旺季与流量": 3, "企业购": 2, "卖家百科": 3, "卖家成长服务": 2,
        "工厂专区": 3, "跨境收付款": 3, "品类洞察": 3, "广告推广": 4
      },
      "lifecycle_relevance": {
        "新手指南": ["新卖家(P2L以前)", "新卖家(P2L)", "新卖家(L2L)"],
        "选品": ["新卖家(P2L)", "新卖家(L2L)", "1年以下卖家"],
        "合规": ["新卖家(L2L)", "1年以下卖家", "1-2年卖家"],
        "物流仓储": ["新卖家(L2L)", "1年以下卖家", "1-2年卖家"],
        "品牌打造": ["1-2年卖家", "2-3年卖家", "3年以上卖家"],
        "旺季与流量": ["1年以下卖家", "1-2年卖家", "2-3年卖家", "3年以上卖家"],
        "广告推广": ["1年以下卖家", "1-2年卖家", "2-3年卖家"]
      }
    }
  },

  "推演规则": {
    "lifecycle_journey": {
      "认知期": {
        "身份": ["新卖家(P2L以前)"],
        "典型问题模式": [
          "{站点}跨境电商怎么做",
          "亚马逊全球开店值得做吗",
          "做亚马逊{站点}需要多少钱",
          "跨境电商和国内电商有什么区别",
          "亚马逊{站点}卖东西赚钱吗",
          "新手做跨境电商难不难",
          "中国卖家做亚马逊{站点}有什么优势",
          "亚马逊全球开店是什么",
          "没经验能做亚马逊吗",
          "亚马逊{站点}适合什么人做"
        ]
      },
      "考虑期": {
        "身份": ["新卖家(P2L以前)", "新卖家(P2L)"],
        "典型问题模式": [
          "亚马逊{站点}和{竞品}哪个好",
          "{企业类型}适合做亚马逊吗",
          "亚马逊{站点}开店成本多少",
          "{年销售额}的公司做亚马逊有优势吗",
          "亚马逊{站点}竞争大吗",
          "做亚马逊{站点}需要准备什么",
          "亚马逊{站点}利润率一般多少",
          "亚马逊和独立站哪个好做",
          "亚马逊{站点}卖什么品类好",
          "做亚马逊需要多少启动资金"
        ]
      },
      "决策期": {
        "身份": ["新卖家(P2L)"],
        "典型问题模式": [
          "亚马逊{站点}注册需要什么材料",
          "{企业类型}注册亚马逊流程",
          "亚马逊个人和企业账号区别",
          "注册亚马逊{站点}要多久",
          "亚马逊{站点}开店全流程",
          "注册亚马逊需要什么公司资质",
          "亚马逊{站点}开店费用清单",
          "亚马逊注册被拒绝的原因有哪些",
          "亚马逊{站点}新手注册攻略",
          "怎么注册亚马逊卖家账号"
        ]
      },
      "注册期": {
        "身份": ["新卖家(L2L)"],
        "典型问题模式": [
          "亚马逊注册审核不通过怎么办",
          "亚马逊{站点}审核需要什么材料",
          "亚马逊二审怎么处理",
          "注册亚马逊后第一步做什么",
          "亚马逊注册要多久才能通过",
          "亚马逊注册资料怎么准备",
          "亚马逊{站点}视频审核怎么过",
          "亚马逊注册地址证明怎么弄",
          "注册亚马逊需要哪些证件",
          "亚马逊注册后台怎么设置"
        ]
      },
      "新手期": {
        "身份": ["新卖家(L2L)", "1年以下卖家"],
        "典型问题模式": [
          "亚马逊{内容分类}怎么做",
          "亚马逊{站点}{内容分类}指南",
          "{发货方式}和自发货哪个好",
          "亚马逊新手怎么{内容分类}",
          "亚马逊{站点}新手第一个产品怎么上架",
          "亚马逊FBA发货流程步骤",
          "亚马逊{站点}{内容分类}注意事项",
          "亚马逊新卖家怎么快速出单",
          "亚马逊{站点}listing怎么优化",
          "新手做亚马逊{站点}常见错误"
        ]
      },
      "成长期": {
        "身份": ["1年以下卖家", "1-2年卖家"],
        "典型问题模式": [
          "亚马逊{内容分类}技巧",
          "如何提升亚马逊{站点}销量",
          "亚马逊{站点}广告怎么投",
          "亚马逊品牌注册有什么好处",
          "亚马逊{站点}PPC广告优化方法",
          "亚马逊{站点}如何做站外引流",
          "亚马逊{内容分类}实操策略",
          "亚马逊{站点}如何提升排名",
          "亚马逊评价怎么增加",
          "亚马逊{站点}旺季怎么备货"
        ]
      },
      "成熟期": {
        "身份": ["2-3年卖家", "3年以上卖家"],
        "典型问题模式": [
          "亚马逊多站点运营策略",
          "亚马逊{站点}合规新规{年份}",
          "亚马逊品牌旗舰店怎么做",
          "亚马逊{站点}VAT税务要求",
          "亚马逊{站点}品牌广告高阶玩法",
          "亚马逊多账号运营风险和方案",
          "亚马逊{站点}自动广告和手动广告怎么配合",
          "亚马逊{站点}如何防跟卖",
          "亚马逊品牌分析工具怎么用",
          "亚马逊{站点}库存管理最佳实践"
        ]
      }
    },

    "priority_formula": {
      "description": "综合优先级 = 身份权重 × 话题权重 × 站点权重 × 生命周期匹配加分",
      "formula": "priority = (identity_weight × 0.3) + (topic_weight × 0.3) + (site_weight × 0.2) + (lifecycle_match × 0.2)",
      "threshold": {
        "P0": "score >= 4.0",
        "P1": "score >= 3.0",
        "P2": "score >= 2.0",
        "P3": "score < 2.0"
      }
    },

    "volume_estimation": {
      "description": "预估热度 = 身份搜索量系数 × 站点搜索量系数 × 话题基础热度",
      "base_volume": {
        "新手指南": 5000, "选品": 3000, "合规": 2000, "物流仓储": 2500,
        "品牌打造": 1500, "旺季与流量": 2000, "企业购": 800, "卖家百科": 1200,
        "卖家成长服务": 600, "工厂专区": 1000, "跨境收付款": 1500, "品类洞察": 1800, "广告推广": 2800
      },
      "formula": "estimated_volume = base_volume × identity_multiplier × site_multiplier"
    },

    "conflict_rules": [
      {"rule": "身份=服务商 时排除 内容分类=新手指南", "reason": "服务商不需要新手指南"},
      {"rule": "身份=3年以上卖家 时排除 内容分类=新手指南", "reason": "老卖家不搜新手内容"},
      {"rule": "年销售额=1亿以上 时排除 身份=新卖家*", "reason": "矛盾组合"},
      {"rule": "企业类型=个人 时降权 发货方式=FBA", "reason": "个人卖家FBA比例低"},
      {"rule": "站点=印度站 时排除 内容分类=企业购", "reason": "印度站无企业购"}
    ]
  },

  "短语来源标签": {
    "collected": "正面渠道收集（SEO/SEM、AI下拉、逆向召回、社区原生）",
    "calibrated": "校准验证（智测已验证的短语）",
    "predicted_p0": "画像推演-P0核心（高置信度预测）",
    "predicted_p1": "画像推演-P1重要（中置信度预测）",
    "predicted_p2": "画像推演-P2长尾（低置信度预测）",
    "zhiyu_forecast": "智预模块推演（信号驱动预测）"
  }
}
