{
    "borderRadiusDesktop": "none",
    "borderRadiusTablet": "desktop",
    "borderRadiusMobileportrait": "tablet",
    "borderRadiusMobilelandscape": "tablet",
    "widthDesktop": 12,
    "widthTablet": 12,
    "widthMobileportrait": 12,
    "widthMobilelandscape": 12,
    "imageOrVideoBg": "image",
    "backgroundURL": "",
    "videoBackgroundURL": "",
    "secondaryVideoBackgroundURL": "",
    "posterURL": "",
    "videoAttrs": ["autoPlay", "muted", "loop", "playsInline"],
    "videoCaptions": [],
    "backgroundPosition": "center center",
    "backgroundSize": "cover",
    "backgroundRepeat": "no-repeat",
    "hyphens": "manual",
    "overflowWrap": "normal",
    "wordBreak": "normal",
    "elementId": "",
    "cssClass": "",
    "data": [],
    "language": "default",
    "deviceColumnsTablet": false,
    "deviceColumnsMobileportrait": false,
    "deviceColumnsMobilelandscape": false,
    "horizontalAlignmentDesktop": "default",
    "horizontalAlignmentTablet": "desktop",
    "horizontalAlignmentMobileportrait": "tablet",
    "horizontalAlignmentMobilelandscape": "tablet",
    "verticalItemsAlignmentDesktop": "stretch",
    "verticalItemsAlignmentTablet": "desktop",
    "verticalItemsAlignmentMobileportrait": "tablet",
    "verticalItemsAlignmentMobilelandscape": "tablet",
    "verticalContentAlignmentDesktop": "flex-start",
    "verticalContentAlignmentTablet": "desktop",
    "verticalContentAlignmentMobileportrait": "tablet",
    "verticalContentAlignmentMobilelandscape": "tablet",
    "isFullHeight": false,
    "hasMaxWidth": true,
    "deviceAvailability": ["desktop", "tablet", "mobilePortrait"],
    "isSticky": false,
    "stickyPosition": "top",
    "animateOnScrollType": "none",
    "animateOnScrollDelay": "100",
    "animateOnScrollDuration": "600",
    "preventImageOptimization": false,
    "inputDependency": false,
    "inputDependencies": [],
    "queryDependency": false,
    "queryDependencies": [],
    "borderWidthTopDesktop": "zero",
    "borderWidthTopTablet": "desktop",
    "borderWidthTopMobileportrait": "tablet",
    "borderWidthTopMobilelandscape": "tablet",
    "borderWidthLeftDesktop": "zero",
    "borderWidthLeftTablet": "desktop",
    "borderWidthLeftMobileportrait": "tablet",
    "borderWidthLeftMobilelandscape": "tablet",
    "borderWidthRightDesktop": "zero",
    "borderWidthRightTablet": "desktop",
    "borderWidthRightMobileportrait": "tablet",
    "borderWidthRightMobilelandscape": "tablet",
    "borderWidthBottomDesktop": "zero",
    "borderWidthBottomTablet": "desktop",
    "borderWidthBottomMobileportrait": "tablet",
    "borderWidthBottomMobilelandscape": "tablet",
    "paddingTopDesktop": "minibase",
    "paddingTopTablet": "base",
    "paddingTopMobileportrait": "tablet",
    "paddingTopMobilelandscape": "tablet",
    "paddingLeftDesktop": "xxlarge",
    "paddingLeftTablet": "xsmall",
    "paddingLeftMobileportrait": "tablet",
    "paddingLeftMobilelandscape": "tablet",
    "paddingRightDesktop": "xxlarge",
    "paddingRightTablet": "xsmall",
    "paddingRightMobileportrait": "tablet",
    "paddingRightMobilelandscape": "tablet",
    "paddingBottomDesktop": "minibase",
    "paddingBottomTablet": "desktop",
    "paddingBottomMobileportrait": "tablet",
    "paddingBottomMobilelandscape": "tablet",
    "hasWave": false,
    "waveStyle": "style-1",
    "waveColor": "white",
    "flipWave": false,
    "wavePlacement": "bottom",
    "hasBoxShadow": false,
    "boxShadowType": "light",
    "isFluid": false,
    "noWrap": false,
    "isMobileRow": false,
    "backgroundColor": "transparent",
    "borderColor": "squid-ink",
    "gradientAngle": "90deg",
    "isSearchAnchor": false,
    "searchAnchorText": "",
    "hoverAnimation": "none",
    "hoverSpeed": "normal",
    "sellDesignSnippetClass": "",
    "tabId": "",
    "showTabOnLoad": false,
    "widgetClassName": "Container",
    "reusable": null,
    "reusablePlaceholder": null,
    "id": "f9c34341-d9b7-4139-8827-8ee5ae6d82d2",
    "widgets": [{
        "borderRadiusDesktop": "none",
        "borderRadiusTablet": "desktop",
        "borderRadiusMobileportrait": "tablet",
        "borderRadiusMobilelandscape": "tablet",
        "widthDesktop": 9,
        "widthTablet": 12,
        "widthMobileportrait": 12,
        "widthMobilelandscape": 12,
        "imageOrVideoBg": "image",
        "backgroundURL": "",
        "videoBackgroundURL": "",
        "secondaryVideoBackgroundURL": "",
        "posterURL": "",
        "videoAttrs": ["autoPlay", "muted", "loop", "playsInline"],
        "videoCaptions": [],
        "backgroundPosition": "center center",
        "backgroundSize": "cover",
        "backgroundRepeat": "no-repeat",
        "hyphens": "manual",
        "overflowWrap": "normal",
        "wordBreak": "normal",
        "elementId": "",
        "cssClass": "",
        "data": [],
        "language": "default",
        "deviceColumnsTablet": false,
        "deviceColumnsMobileportrait": false,
        "deviceColumnsMobilelandscape": false,
        "horizontalAlignmentDesktop": "default",
        "horizontalAlignmentTablet": "desktop",
        "horizontalAlignmentMobileportrait": "tablet",
        "horizontalAlignmentMobilelandscape": "tablet",
        "verticalItemsAlignmentDesktop": "stretch",
        "verticalItemsAlignmentTablet": "desktop",
        "verticalItemsAlignmentMobileportrait": "tablet",
        "verticalItemsAlignmentMobilelandscape": "tablet",
        "verticalContentAlignmentDesktop": "flex-start",
        "verticalContentAlignmentTablet": "desktop",
        "verticalContentAlignmentMobileportrait": "tablet",
        "verticalContentAlignmentMobilelandscape": "tablet",
        "isFullHeight": false,
        "hasMaxWidth": false,
        "deviceAvailability": ["desktop", "tablet", "mobilePortrait", "mobileLandscape"],
        "isSticky": false,
        "stickyPosition": "top",
        "animateOnScrollType": "none",
        "animateOnScrollDelay": "100",
        "animateOnScrollDuration": "600",
        "preventImageOptimization": false,
        "inputDependency": false,
        "inputDependencies": [],
        "queryDependency": false,
        "queryDependencies": [],
        "borderWidthTopDesktop": "zero",
        "borderWidthTopTablet": "desktop",
        "borderWidthTopMobileportrait": "tablet",
        "borderWidthTopMobilelandscape": "tablet",
        "borderWidthLeftDesktop": "zero",
        "borderWidthLeftTablet": "desktop",
        "borderWidthLeftMobileportrait": "tablet",
        "borderWidthLeftMobilelandscape": "tablet",
        "borderWidthRightDesktop": "1px",
        "borderWidthRightTablet": "zero",
        "borderWidthRightMobileportrait": "tablet",
        "borderWidthRightMobilelandscape": "tablet",
        "borderWidthBottomDesktop": "zero",
        "borderWidthBottomTablet": "desktop",
        "borderWidthBottomMobileportrait": "tablet",
        "borderWidthBottomMobilelandscape": "tablet",
        "paddingTopDesktop": "zero",
        "paddingTopTablet": "desktop",
        "paddingTopMobileportrait": "tablet",
        "paddingTopMobilelandscape": "tablet",
        "paddingLeftDesktop": "base",
        "paddingLeftTablet": "zero",
        "paddingLeftMobileportrait": "tablet",
        "paddingLeftMobilelandscape": "tablet",
        "paddingRightDesktop": "base",
        "paddingRightTablet": "zero",
        "paddingRightMobileportrait": "tablet",
        "paddingRightMobilelandscape": "tablet",
        "paddingBottomDesktop": "zero",
        "paddingBottomTablet": "zero",
        "paddingBottomMobileportrait": "tablet",
        "paddingBottomMobilelandscape": "tablet",
        "hasWave": false,
        "waveStyle": "style-1",
        "waveColor": "white",
        "flipWave": false,
        "wavePlacement": "bottom",
        "hasBoxShadow": false,
        "boxShadowType": "light",
        "isFluid": false,
        "noWrap": false,
        "isMobileRow": false,
        "backgroundColor": "transparent",
        "borderColor": "cumulus",
        "gradientAngle": "90deg",
        "isSearchAnchor": false,
        "searchAnchorText": "",
        "hoverAnimation": "none",
        "hoverSpeed": "normal",
        "sellDesignSnippetClass": "",
        "tabId": "",
        "showTabOnLoad": false,
        "widgetClassName": "Container",
        "reusable": null,
        "reusablePlaceholder": null,
        "id": "42d557d6-4a62-4995-bb61-38477c49d5f6",
        "widgets": [{
            "borderRadiusDesktop": "none",
            "borderRadiusTablet": "desktop",
            "borderRadiusMobileportrait": "tablet",
            "borderRadiusMobilelandscape": "tablet",
            "widthDesktop": 12,
            "widthTablet": 12,
            "widthMobileportrait": 12,
            "widthMobilelandscape": 12,
            "imageOrVideoBg": "image",
            "backgroundURL": "",
            "videoBackgroundURL": "",
            "secondaryVideoBackgroundURL": "",
            "posterURL": "",
            "videoAttrs": ["autoPlay", "muted", "loop", "playsInline"],
            "videoCaptions": [],
            "backgroundPosition": "center center",
            "backgroundSize": "cover",
            "backgroundRepeat": "no-repeat",
            "hyphens": "manual",
            "overflowWrap": "normal",
            "wordBreak": "normal",
            "elementId": "",
            "cssClass": "",
            "data": [],
            "language": "default",
            "deviceColumnsTablet": false,
            "deviceColumnsMobileportrait": false,
            "deviceColumnsMobilelandscape": false,
            "horizontalAlignmentDesktop": "default",
            "horizontalAlignmentTablet": "desktop",
            "horizontalAlignmentMobileportrait": "tablet",
            "horizontalAlignmentMobilelandscape": "tablet",
            "verticalItemsAlignmentDesktop": "stretch",
            "verticalItemsAlignmentTablet": "desktop",
            "verticalItemsAlignmentMobileportrait": "tablet",
            "verticalItemsAlignmentMobilelandscape": "tablet",
            "verticalContentAlignmentDesktop": "flex-start",
            "verticalContentAlignmentTablet": "desktop",
            "verticalContentAlignmentMobileportrait": "tablet",
            "verticalContentAlignmentMobilelandscape": "tablet",
            "isFullHeight": false,
            "hasMaxWidth": false,
            "deviceAvailability": ["desktop", "tablet", "mobilePortrait", "mobileLandscape"],
            "isSticky": false,
            "stickyPosition": "top",
            "animateOnScrollType": "none",
            "animateOnScrollDelay": "100",
            "animateOnScrollDuration": "600",
            "preventImageOptimization": false,
            "inputDependency": false,
            "inputDependencies": [],
            "queryDependency": false,
            "queryDependencies": [],
            "borderWidthTopDesktop": "zero",
            "borderWidthTopTablet": "desktop",
            "borderWidthTopMobileportrait": "tablet",
            "borderWidthTopMobilelandscape": "tablet",
            "borderWidthLeftDesktop": "zero",
            "borderWidthLeftTablet": "desktop",
            "borderWidthLeftMobileportrait": "tablet",
            "borderWidthLeftMobilelandscape": "tablet",
            "borderWidthRightDesktop": "zero",
            "borderWidthRightTablet": "desktop",
            "borderWidthRightMobileportrait": "tablet",
            "borderWidthRightMobilelandscape": "tablet",
            "borderWidthBottomDesktop": "zero",
            "borderWidthBottomTablet": "desktop",
            "borderWidthBottomMobileportrait": "tablet",
            "borderWidthBottomMobilelandscape": "tablet",
            "paddingTopDesktop": "zero",
            "paddingTopTablet": "desktop",
            "paddingTopMobileportrait": "tablet",
            "paddingTopMobilelandscape": "tablet",
            "paddingLeftDesktop": "zero",
            "paddingLeftTablet": "desktop",
            "paddingLeftMobileportrait": "tablet",
            "paddingLeftMobilelandscape": "tablet",
            "paddingRightDesktop": "zero",
            "paddingRightTablet": "desktop",
            "paddingRightMobileportrait": "tablet",
            "paddingRightMobilelandscape": "tablet",
            "paddingBottomDesktop": "zero",
            "paddingBottomTablet": "desktop",
            "paddingBottomMobileportrait": "tablet",
            "paddingBottomMobilelandscape": "tablet",
            "hasWave": false,
            "waveStyle": "style-1",
            "waveColor": "white",
            "flipWave": false,
            "wavePlacement": "bottom",
            "hasBoxShadow": false,
            "boxShadowType": "light",
            "isFluid": false,
            "noWrap": false,
            "isMobileRow": false,
            "backgroundColor": "transparent",
            "borderColor": "squid-ink",
            "gradientAngle": "0deg",
            "isSearchAnchor": false,
            "searchAnchorText": "",
            "hoverAnimation": "none",
            "hoverSpeed": "normal",
            "sellDesignSnippetClass": "",
            "tabId": "",
            "showTabOnLoad": false,
            "widgetClassName": "Container",
            "reusable": null,
            "reusablePlaceholder": null,
            "id": "bef0b35b-3a3e-4c26-80fa-ca17da71e91d",
            "widgets": [{
                "widgetClassName": "Spacer",
                "reusable": null,
                "reusablePlaceholder": null,
                "id": "15f48b22-1734-4abd-bdf1-9f14d50de9d8"
            }]
        }, {
            "borderRadiusDesktop": "none",
            "borderRadiusTablet": "desktop",
            "borderRadiusMobileportrait": "tablet",
            "borderRadiusMobilelandscape": "tablet",
            "widthDesktop": 12,
            "widthTablet": 12,
            "widthMobileportrait": 12,
            "widthMobilelandscape": 12,
            "imageOrVideoBg": "image",
            "backgroundURL": "",
            "videoBackgroundURL": "",
            "secondaryVideoBackgroundURL": "",
            "posterURL": "",
            "videoAttrs": ["autoPlay", "muted", "loop", "playsInline"],
            "videoCaptions": [],
            "backgroundPosition": "center center",
            "backgroundSize": "cover",
            "backgroundRepeat": "no-repeat",
            "hyphens": "manual",
            "overflowWrap": "normal",
            "wordBreak": "normal",
            "elementId": "",
            "cssClass": "",
            "data": [],
            "language": "default",
            "deviceColumnsTablet": false,
            "deviceColumnsMobileportrait": false,
            "deviceColumnsMobilelandscape": false,
            "horizontalAlignmentDesktop": "default",
            "horizontalAlignmentTablet": "desktop",
            "horizontalAlignmentMobileportrait": "tablet",
            "horizontalAlignmentMobilelandscape": "tablet",
            "verticalItemsAlignmentDesktop": "stretch",
            "verticalItemsAlignmentTablet": "desktop",
            "verticalItemsAlignmentMobileportrait": "tablet",
            "verticalItemsAlignmentMobilelandscape": "tablet",
            "verticalContentAlignmentDesktop": "flex-start",
            "verticalContentAlignmentTablet": "desktop",
            "verticalContentAlignmentMobileportrait": "tablet",
            "verticalContentAlignmentMobilelandscape": "tablet",
            "isFullHeight": false,
            "hasMaxWidth": false,
            "deviceAvailability": ["desktop", "tablet", "mobilePortrait", "mobileLandscape"],
            "isSticky": false,
            "stickyPosition": "top",
            "animateOnScrollType": "none",
            "animateOnScrollDelay": "100",
            "animateOnScrollDuration": "600",
            "preventImageOptimization": false,
            "inputDependency": false,
            "inputDependencies": [],
            "queryDependency": false,
            "queryDependencies": [],
            "borderWidthTopDesktop": "zero",
            "borderWidthTopTablet": "desktop",
            "borderWidthTopMobileportrait": "tablet",
            "borderWidthTopMobilelandscape": "tablet",
            "borderWidthLeftDesktop": "zero",
            "borderWidthLeftTablet": "desktop",
            "borderWidthLeftMobileportrait": "tablet",
            "borderWidthLeftMobilelandscape": "tablet",
            "borderWidthRightDesktop": "zero",
            "borderWidthRightTablet": "desktop",
            "borderWidthRightMobileportrait": "tablet",
            "borderWidthRightMobilelandscape": "tablet",
            "borderWidthBottomDesktop": "zero",
            "borderWidthBottomTablet": "desktop",
            "borderWidthBottomMobileportrait": "tablet",
            "borderWidthBottomMobilelandscape": "tablet",
            "paddingTopDesktop": "zero",
            "paddingTopTablet": "desktop",
            "paddingTopMobileportrait": "tablet",
            "paddingTopMobilelandscape": "tablet",
            "paddingLeftDesktop": "zero",
            "paddingLeftTablet": "desktop",
            "paddingLeftMobileportrait": "tablet",
            "paddingLeftMobilelandscape": "tablet",
            "paddingRightDesktop": "zero",
            "paddingRightTablet": "desktop",
            "paddingRightMobileportrait": "tablet",
            "paddingRightMobilelandscape": "tablet",
            "paddingBottomDesktop": "base",
            "paddingBottomTablet": "zero",
            "paddingBottomMobileportrait": "tablet",
            "paddingBottomMobilelandscape": "tablet",
            "hasWave": false,
            "waveStyle": "style-1",
            "waveColor": "white",
            "flipWave": false,
            "wavePlacement": "bottom",
            "hasBoxShadow": false,
            "boxShadowType": "light",
            "isFluid": false,
            "noWrap": false,
            "isMobileRow": false,
            "backgroundColor": "transparent",
            "borderColor": "squid-ink",
            "gradientAngle": "90deg",
            "isSearchAnchor": false,
            "searchAnchorText": "",
            "hoverAnimation": "none",
            "hoverSpeed": "normal",
            "sellDesignSnippetClass": "",
            "tabId": "",
            "showTabOnLoad": false,
            "widgetClassName": "Container",
            "reusable": null,
            "reusablePlaceholder": null,
            "id": "7198507f-5e5e-455c-a652-dcc665487ae6",
            "widgets": [{
                "widgetClassName": "Spacer",
                "reusable": null,
                "reusablePlaceholder": null,
                "id": "5fd0dd68-0bf5-4c29-bc95-88b9b54859ae"
            }]
        }]
    }, {
        "borderRadiusDesktop": "none",
        "borderRadiusTablet": "desktop",
        "borderRadiusMobileportrait": "tablet",
        "borderRadiusMobilelandscape": "tablet",
        "widthDesktop": 3,
        "widthTablet": 12,
        "widthMobileportrait": 12,
        "widthMobilelandscape": 12,
        "imageOrVideoBg": "image",
        "backgroundURL": "",
        "videoBackgroundURL": "",
        "secondaryVideoBackgroundURL": "",
        "posterURL": "",
        "videoAttrs": ["autoPlay", "muted", "loop", "playsInline"],
        "videoCaptions": [],
        "backgroundPosition": "center center",
        "backgroundSize": "cover",
        "backgroundRepeat": "no-repeat",
        "hyphens": "manual",
        "overflowWrap": "normal",
        "wordBreak": "normal",
        "elementId": "",
        "cssClass": "",
        "data": [],
        "language": "default",
        "deviceColumnsTablet": false,
        "deviceColumnsMobileportrait": false,
        "deviceColumnsMobilelandscape": false,
        "horizontalAlignmentDesktop": "default",
        "horizontalAlignmentTablet": "desktop",
        "horizontalAlignmentMobileportrait": "tablet",
        "horizontalAlignmentMobilelandscape": "tablet",
        "verticalItemsAlignmentDesktop": "stretch",
        "verticalItemsAlignmentTablet": "desktop",
        "verticalItemsAlignmentMobileportrait": "tablet",
        "verticalItemsAlignmentMobilelandscape": "tablet",
        "verticalContentAlignmentDesktop": "flex-start",
        "verticalContentAlignmentTablet": "desktop",
        "verticalContentAlignmentMobileportrait": "tablet",
        "verticalContentAlignmentMobilelandscape": "tablet",
        "isFullHeight": false,
        "hasMaxWidth": false,
        "deviceAvailability": ["desktop", "tablet", "mobilePortrait", "mobileLandscape"],
        "isSticky": false,
        "stickyPosition": "top",
        "animateOnScrollType": "none",
        "animateOnScrollDelay": "100",
        "animateOnScrollDuration": "600",
        "preventImageOptimization": false,
        "inputDependency": false,
        "inputDependencies": [],
        "queryDependency": false,
        "queryDependencies": [],
        "borderWidthTopDesktop": "zero",
        "borderWidthTopTablet": "desktop",
        "borderWidthTopMobileportrait": "tablet",
        "borderWidthTopMobilelandscape": "tablet",
        "borderWidthLeftDesktop": "zero",
        "borderWidthLeftTablet": "desktop",
        "borderWidthLeftMobileportrait": "tablet",
        "borderWidthLeftMobilelandscape": "tablet",
        "borderWidthRightDesktop": "zero",
        "borderWidthRightTablet": "desktop",
        "borderWidthRightMobileportrait": "tablet",
        "borderWidthRightMobilelandscape": "tablet",
        "borderWidthBottomDesktop": "zero",
        "borderWidthBottomTablet": "desktop",
        "borderWidthBottomMobileportrait": "tablet",
        "borderWidthBottomMobilelandscape": "tablet",
        "paddingTopDesktop": "zero",
        "paddingTopTablet": "desktop",
        "paddingTopMobileportrait": "tablet",
        "paddingTopMobilelandscape": "tablet",
        "paddingLeftDesktop": "zero",
        "paddingLeftTablet": "desktop",
        "paddingLeftMobileportrait": "tablet",
        "paddingLeftMobilelandscape": "tablet",
        "paddingRightDesktop": "zero",
        "paddingRightTablet": "zero",
        "paddingRightMobileportrait": "tablet",
        "paddingRightMobilelandscape": "tablet",
        "paddingBottomDesktop": "zero",
        "paddingBottomTablet": "base",
        "paddingBottomMobileportrait": "tablet",
        "paddingBottomMobilelandscape": "tablet",
        "hasWave": false,
        "waveStyle": "style-1",
        "waveColor": "white",
        "flipWave": false,
        "wavePlacement": "bottom",
        "hasBoxShadow": false,
        "boxShadowType": "light",
        "isFluid": false,
        "noWrap": false,
        "isMobileRow": false,
        "backgroundColor": "transparent",
        "borderColor": "squid-ink",
        "gradientAngle": "0deg",
        "isSearchAnchor": false,
        "searchAnchorText": "",
        "hoverAnimation": "none",
        "hoverSpeed": "normal",
        "sellDesignSnippetClass": "",
        "tabId": "",
        "showTabOnLoad": false,
        "widgetClassName": "Container",
        "reusable": null,
        "reusablePlaceholder": null,
        "id": "155285f5-ec38-40f1-afa4-fd07983efebb",
        "widgets": [{
            "widgetClassName": "Spacer",
            "reusable": null,
            "reusablePlaceholder": null,
            "id": "473f3933-5a2b-4c77-8150-04b68ae8e2a5"
        }]
    }],
    "design": "Sell",
    "uuid": "50d4fd30-4f5b-11f1-a647-f7eba79e15d4",
    "legoVersion": "2"
}